{
  "meta": {
    "stableOrder": true
  },
  "lockfileVersion": 3,
  "ATTENTION": "THIS IS AN AUTOGENERATED FILE. DO NOT EDIT THIS FILE DIRECTLY.",
  "specifiers": {
    "simple-native-ohos@^1.0.3": "simple-native-ohos@1.0.3"
  },
  "packages": {
    "simple-native-ohos@1.0.3": {
      "name": "simple-native-ohos",
      "version": "1.0.3",
      "integrity": "sha512-sIqXScgDjAePCRAZe9S20L5oZFQw+rlOzejizifgkfnCGuZlrA6MFVwgOmtwYN5bPNv+0UKkIBI1SrHEtQBwyg==",
      "resolved": "https://ohpm.openharmony.cn/ohpm/simple-native-ohos/-/simple-native-ohos-1.0.3.har",
      "registryType": "ohpm"
    }
  }
}